torch_hep/__init__.py
torch_hep/lorentz.py
torch_hep/data/TensorLoader.py
torch_hep/data/__init__.py
torch_hep/graph/GraphBuilder.py
torch_hep/graph/__init__.py
torch_hep-0.0.4.dist-info/LICENSE
torch_hep-0.0.4.dist-info/METADATA
torch_hep-0.0.4.dist-info/WHEEL
torch_hep-0.0.4.dist-info/top_level.txt
torch_hep-0.0.4.dist-info/RECORD
